pyTBA-1.2.1.dist-info/DESCRIPTION.rst
pyTBA-1.2.1.dist-info/METADATA
pyTBA-1.2.1.dist-info/RECORD
pyTBA-1.2.1.dist-info/WHEEL
pyTBA-1.2.1.dist-info/metadata.json
pyTBA-1.2.1.dist-info/top_level.txt
pytba/__init__.py
pytba/api.py
pytba/models.py
pytba/stats.py
pytba/util.py
pytba/game_constants/__init__.py
pytba/game_constants/stronghold2016.py
pytba/test/__init__.py
pytba/test/api_test.py
pytba/test/stats_test.py
pytba/test/tests.py
pytba/test/util_test.py
