Metadata-Version: 1.1
Name: pyTBA
Version: 1.2.1
Summary: Python implementation for The Blue Alliance API
Home-page: https://github.com/Thing342/pyTBA
Author: Wes Jordan
Author-email: wes@wesj.org
License: GPLv3
Keywords: Python implementation of Blue Alliance API for FRC
Platform: UNKNOWN
Classifier: Development Status :: 4 - Beta
Classifier: Intended Audience :: Developers
Classifier: Topic :: Software Development :: Libraries
Classifier: License :: OSI Approved :: GNU General Public License v3 (GPLv3)
Classifier: Programming Language :: Python :: 3.3
Classifier: Programming Language :: Python :: 3.4
Classifier: Programming Language :: Python :: 3.5
